flask_ninja/__init__.py
flask_ninja/api.py
flask_ninja/constants.py
flask_ninja/model_field.py
flask_ninja/models.py
flask_ninja/operation.py
flask_ninja/param.py
flask_ninja/param_functions.py
flask_ninja/parse_rule.py
flask_ninja/py.typed
flask_ninja/router.py
flask_ninja/security.py
flask_ninja/swagger-ui-5.9.1/README.md
flask_ninja/swagger-ui-5.9.1/favicon-16x16.png
flask_ninja/swagger-ui-5.9.1/favicon-32x32.png
flask_ninja/swagger-ui-5.9.1/index.j2
flask_ninja/swagger-ui-5.9.1/py.typed
flask_ninja/swagger-ui-5.9.1/swagger-ui-bundle.js
flask_ninja/swagger-ui-5.9.1/swagger-ui-standalone-preset.js
flask_ninja/swagger-ui-5.9.1/swagger-ui.css
flask_ninja/swagger_ui.py
flask_ninja/utils.py
flask_ninja-1.3.0.dist-info/METADATA
flask_ninja-1.3.0.dist-info/WHEEL
flask_ninja-1.3.0.dist-info/RECORD
