Metadata-Version: 2.1
Name: flask-ninja
Version: 1.3.0
Summary: Flask Ninja is a web framework for building APIs with Flask and Python 3.9+ type hints.
Author: Michal Korbela
Author-email: michal.korbela@kiwi.com
Requires-Python: >=3.9,<4.0
Classifier: Programming Language :: Python :: 3
Classifier: Programming Language :: Python :: 3.9
Classifier: Programming Language :: Python :: 3.10
Classifier: Programming Language :: Python :: 3.11
Classifier: Programming Language :: Python :: 3.12
Requires-Dist: Flask (>=2.3.0)
Requires-Dist: docstring-parser (>=0.14.1,<0.15.0)
Requires-Dist: pydantic (>=2.4.2,<3.0.0)
